mailjet_utils/__init__.py
mailjet_utils/app.py
mailjet_utils/models.py
mailjet_utils-0.2.0.dist-info/WHEEL
mailjet_utils-0.2.0.dist-info/METADATA
mailjet_utils-0.2.0.dist-info/RECORD
