Metadata-Version: 2.1
Name: mailjet-utils
Version: 0.2.0
Summary: A package with models for working with mailjet.
Home-page: https://www.github.com/peder2911/mailjet_utils
Author: peder2911
Author-email: pglandsverk@gmail.com
Requires-Python: >=3.8,<4.0
Classifier: Programming Language :: Python :: 3
Classifier: Programming Language :: Python :: 3.10
Classifier: Programming Language :: Python :: 3.8
Classifier: Programming Language :: Python :: 3.9
Requires-Dist: fastapi (>=0.74.1,<0.75.0)
Requires-Dist: gunicorn (>=20.1.0,<21.0.0)
Requires-Dist: httptools (>=0.3.0,<0.4.0)
Requires-Dist: pydantic[email] (>=1.9.0,<2.0.0)
Requires-Dist: uvicorn (>=0.17.5,<0.18.0)
Requires-Dist: uvloop (>=0.16.0,<0.17.0)
